r2angrdbg/__init__.py
r2angrdbg-1.0.1.dist-info/LICENSE
r2angrdbg-1.0.1.dist-info/METADATA
r2angrdbg-1.0.1.dist-info/WHEEL
r2angrdbg-1.0.1.dist-info/top_level.txt
r2angrdbg-1.0.1.dist-info/RECORD
