Metadata-Version: 2.1
Name: r2angrdbg
Version: 1.0.1
Summary: Use angr inside the radare2 debugger. Create an angr state from the current debugger state. 
Home-page: https://github.com/andreafioraldi/r2angrdbg
Author: Andrea Fioraldi
Author-email: andreafioraldi@gmail.com
License: BSD 2-Clause
Download-URL: https://github.com/andreafioraldi/r2angrdbg/archive/1.0.1.tar.gz
Platform: UNKNOWN
Requires-Dist: angrdbg
